{"userData":[{"self_user_id":"249623789","user_name":"DorJug","folder_id":"1byS3QeNDSp3rGH4uRe4oI8MP1Fe7Fee3","folders":"string","poll":false,"mode":"","chats":[{"chat_id":"-426586555","user_choose":[],"chat_folder_id":"1RrWvVye81LLnLq12qEGBeonf6zqiVXgS","chat_name":"ляля","filter":false,"full":false,"users":[{"user_id_s":"249623789","folder_id_s":"0","user_name_s":"DorJug"},{"user_id_s":"1331579688","folder_id_s":"1ElWZymsGtHd6466FrvA2LtdnwmoAPIF7","user_name_s":"EvgDeGa"}]},{"chat_id":"-345003261","user_choose":[0],"chat_folder_id":"1siI_E3auT_vcTFVwFhFHdQp5zas0wfi8","chat_name":"тестовая","filter":false,"full":false,"users":[{"user_id_s":"0","folder_id_s":"0","user_name_s":"0"},{"user_id_s":"249623789","folder_id_s":"0","user_name_s":"DorJug"}]}]}],"chatData":[{"chat_id":"-426586555","user_choose":[],"chat_folder_id":" ","chat_name":"ляля","filter":false,"full":true,"users":[{"user_id_s":"249623789","folder_id_s":"0","user_name_s":"DorJug"},{"user_id_s":"1331579688","folder_id_s":"0"},{"user_id_s":"477250534","folder_id_s":"0","user_name_s":"Wiz_Stale"}]},{"chat_id":"-345003261","user_choose":[0],"chat_folder_id":"1siI_E3auT_vcTFVwFhFHdQp5zas0wfi8","chat_name":"тестовая","filter":false,"full":false,"users":[{"user_id_s":"0","folder_id_s":"0","user_name_s":"0"},{"user_id_s":"249623789","folder_id_s":"0","user_name_s":"DorJug"}]},{"chat_id":"249623789","user_choose":[],"chat_folder_id":"","filter":false,"full":false,"users":[{"user_id_s":"0","folder_id_s":"0","user_name_s":"0"},{"user_id_s":"249623789","folder_id_s":"0","user_name_s":"DorJug"}]}]}